add_command/__init__.py
add_command-0.1.0.dist-info/METADATA
add_command-0.1.0.dist-info/WHEEL
add_command-0.1.0.dist-info/entry_points.txt
add_command-0.1.0.dist-info/RECORD
