Metadata-Version: 2.4
Name: add-command
Version: 0.1.0
Summary: Add Claude Code slash commands from GitHub to your project
License-Expression: MIT
Requires-Python: >=3.10
Requires-Dist: agent-resources>=0.1.0
